COPYING
COPYING.lesser
MANIFEST.in
NOTICE
README.md
requirements.txt
setup.py
compiler/__init__.py
compiler/api/__init__.py
compiler/api/compiler.py
compiler/api/source/auth_key.tl
compiler/api/source/main_api.tl
compiler/api/source/sys_msgs.tl
compiler/api/template/combinator.txt
compiler/api/template/type.txt
compiler/docs/__init__.py
compiler/docs/compiler.py
compiler/docs/template/page.txt
compiler/docs/template/toctree.txt
compiler/errors/__init__.py
compiler/errors/compiler.py
compiler/errors/sort.py
compiler/errors/source/303_SEE_OTHER.tsv
compiler/errors/source/400_BAD_REQUEST.tsv
compiler/errors/source/401_UNAUTHORIZED.tsv
compiler/errors/source/403_FORBIDDEN.tsv
compiler/errors/source/406_NOT_ACCEPTABLE.tsv
compiler/errors/source/420_FLOOD.tsv
compiler/errors/source/500_INTERNAL_SERVER_ERROR.tsv
compiler/errors/source/503_SERVICE_UNAVAILABLE.tsv
compiler/errors/template/class.txt
compiler/errors/template/sub_class.txt
pyrogram/__init__.py
pyrogram/client.py
pyrogram/dispatcher.py
pyrogram/emoji.py
pyrogram/file_id.py
pyrogram/filters.py
pyrogram/mime_types.py
pyrogram/py.typed
pyrogram/sync.py
pyrogram/utils.py
pyrogram/connection/__init__.py
pyrogram/connection/connection.py
pyrogram/connection/transport/__init__.py
pyrogram/connection/transport/tcp/__init__.py
pyrogram/connection/transport/tcp/tcp.py
pyrogram/connection/transport/tcp/tcp_abridged.py
pyrogram/connection/transport/tcp/tcp_abridged_o.py
pyrogram/connection/transport/tcp/tcp_full.py
pyrogram/connection/transport/tcp/tcp_intermediate.py
pyrogram/connection/transport/tcp/tcp_intermediate_o.py
pyrogram/crypto/__init__.py
pyrogram/crypto/aes.py
pyrogram/crypto/mtproto.py
pyrogram/crypto/prime.py
pyrogram/crypto/rsa.py
pyrogram/enums/__init__.py
pyrogram/enums/auto_name.py
pyrogram/enums/chat_action.py
pyrogram/enums/chat_event_action.py
pyrogram/enums/chat_member_status.py
pyrogram/enums/chat_members_filter.py
pyrogram/enums/chat_type.py
pyrogram/enums/client_platform.py
sangekgram.egg-info/PKG-INFO
sangekgram.egg-info/SOURCES.txt
sangekgram.egg-info/dependency_links.txt
sangekgram.egg-info/not-zip-safe
sangekgram.egg-info/requires.txt
sangekgram.egg-info/top_level.txt
